pluto2npy/__init__.py
pluto2npy/p2n.py
pluto2npy-0.1.0.dist-info/entry_points.txt
pluto2npy-0.1.0.dist-info/WHEEL
pluto2npy-0.1.0.dist-info/METADATA
pluto2npy-0.1.0.dist-info/RECORD
